{
  "AwiaParams":
  [
    {
      "deviceType":"CAN",
      "deviceNumber":"0xC0",
      "subType":"0x4E",
      "params":
      [
		{"key":"year","awiabit":32,"len":8,"min":0.000000,"max":255.000000,"sign":false,"unit":"-","poly":[2000.000000,1.000000]},
		{"key":"month","awiabit":40,"len":8,"min":1.000000,"max":12.000000,"sign":false,"unit":"-","poly":[0.000000,1.000000]},
		{"key":"day","awiabit":48,"len":8,"min":1.000000,"max":31.000000,"sign":false,"unit":"-","poly":[0.000000,1.000000]},
		{"key":"hour","awiabit":56,"len":8,"min":0.000000,"max":23.000000,"sign":false,"unit":"-","poly":[0.000000,1.000000]},
		{"key":"minute","awiabit":64,"len":8,"min":0.000000,"max":59.000000,"sign":false,"unit":"-","poly":[0.000000,1.000000]},
		{"key":"second","awiabit":72,"len":8,"min":0.000000,"max":59.000000,"sign":false,"unit":"-","poly":[0.000000,1.000000]},
		{"key":"cabA","awiabit":80,"len":1,"min":0.000000,"max":1.000000,"sign":false,"unit":"0/1","poly":[0.000000,1.000000]},
		{"key":"cabB","awiabit":81,"len":1,"min":0.000000,"max":1.000000,"sign":false,"unit":"0/1","poly":[0.000000,1.000000]},
		{"key":"isMultiTraction","awiabit":82,"len":1,"min":0.000000,"max":1.000000,"sign":false,"unit":"0/1","poly":[0.000000,1.000000]},
		{"key":"isMaster","awiabit":83,"len":1,"min":0.000000,"max":1.000000,"sign":false,"unit":"0/1","poly":[0.000000,1.000000]},
		{"key":"isCabAttach","awiabit":84,"len":1,"min":0.000000,"max":1.000000,"sign":false,"unit":"0/1","poly":[0.000000,1.000000]},
		{"key":"canOpenRightDoors","awiabit":85,"len":1,"min":0.000000,"max":1.000000,"sign":false,"unit":"0/1","poly":[0.000000,1.000000]},
		{"key":"canOpenLeftDoors","awiabit":86,"len":1,"min":0.000000,"max":1.000000,"sign":false,"unit":"0/1","poly":[0.000000,1.000000]},
		{"key":"reserve1","awiabit":87,"len":1,"min":0.000000,"max":1.000000,"sign":false,"unit":"0/1","poly":[0.000000,1.000000]},
		{"key":"latitude","awiabit":88,"len":32,"min":-360.000000,"max":360.000000,"sign":true,"unit":"stopnie","poly":[0.000000,1.000000],"type":"float"},
		{"key":"longitude","awiabit":120,"len":32,"min":-180.000000,"max":180.000000,"sign":true,"unit":"stopnie","poly":[0.000000,1.000000],"type":"float"},
		{"key":"userId","awiabit":152,"len":32,"min":0.000000,"max":4294967295.000000,"sign":false,"unit":"-","poly":[0.000000,1.000000]},
		{"key":"distanceFromStart","awiabit":184,"len":24,"min":0.000000,"max":16777215.000000,"sign":false,"unit":"m","poly":[0.000000,1.000000]},
		{"key":"totalDistance","awiabit":208,"len":40,"min":0.000000,"max":4294967295.000000,"sign":false,"unit":"m","poly":[0.000000,1.000000]},
		{"key":"wc1","awiabit":248,"len":1,"min":0.000000,"max":1.000000,"sign":false,"unit":"0/1","poly":[0.000000,1.000000]},
		{"key":"isCouplerA","awiabit":249,"len":1,"min":0.000000,"max":1.000000,"sign":false,"unit":"0/1","poly":[0.000000,1.000000]},
		{"key":"isCouplerB","awiabit":250,"len":1,"min":0.000000,"max":1.000000,"sign":false,"unit":"0/1","poly":[0.000000,1.000000]},
		{"key":"isWc1Fault","awiabit":251,"len":1,"min":0.000000,"max":1.000000,"sign":false,"unit":"0/1","poly":[0.000000,1.000000]},
		{"key":"centralCloseDoorsLeft","awiabit":252,"len":1,"min":0.000000,"max":1.000000,"sign":false,"unit":"0/1","poly":[0.000000,1.000000]},
		{"key":"centralCloseDoorsRight","awiabit":253,"len":1,"min":0.000000,"max":1.000000,"sign":false,"unit":"0/1","poly":[0.000000,1.000000]},
		{"key":"doorCabAZp","awiabit":254,"len":1,"min":0.000000,"max":1.000000,"sign":false,"unit":"0/1","poly":[0.000000,1.000000]},
		{"key":"doorCabBZp","awiabit":255,"len":1,"min":0.000000,"max":1.000000,"sign":false,"unit":"0/1","poly":[0.000000,1.000000]},
		{"key":"controllerBreak","awiabit":256,"len":1,"min":0.000000,"max":1.000000,"sign":false,"unit":"0/1","poly":[0.000000,1.000000]},
		{"key":"fungusBreak","awiabit":257,"len":1,"min":0.000000,"max":1.000000,"sign":false,"unit":"0/1","poly":[0.000000,1.000000]},
		{"key":"radiostopBreak","awiabit":258,"len":1,"min":0.000000,"max":1.000000,"sign":false,"unit":"0/1","poly":[0.000000,1.000000]},
		{"key":"shpBreak","awiabit":259,"len":1,"min":0.000000,"max":1.000000,"sign":false,"unit":"0/1","poly":[0.000000,1.000000]},
		{"key":"sifeBreak","awiabit":260,"len":1,"min":0.000000,"max":1.000000,"sign":false,"unit":"0/1","poly":[0.000000,1.000000]},
		{"key":"aadSystem","awiabit":261,"len":1,"min":0.000000,"max":1.000000,"sign":false,"unit":"0/1","poly":[0.000000,1.000000]},
		{"key":"etcsBreak","awiabit":262,"len":1,"min":0.000000,"max":1.000000,"sign":false,"unit":"0/1","poly":[0.000000,1.000000]},
		{"key":"reserve2","awiabit":263,"len":1,"min":0.000000,"max":1.000000,"sign":false,"unit":"0/1","poly":[0.000000,1.000000]},
		{"key":"safetyBreak1","awiabit":264,"len":1,"min":0.000000,"max":1.000000,"sign":false,"unit":"0/1","poly":[0.000000,1.000000]},
		{"key":"safetyBreak2","awiabit":265,"len":1,"min":0.000000,"max":1.000000,"sign":false,"unit":"0/1","poly":[0.000000,1.000000]},
		{"key":"safetyBreak3","awiabit":266,"len":1,"min":0.000000,"max":1.000000,"sign":false,"unit":"0/1","poly":[0.000000,1.000000]},
		{"key":"safetyBreak4","awiabit":267,"len":1,"min":0.000000,"max":1.000000,"sign":false,"unit":"0/1","poly":[0.000000,1.000000]},
		{"key":"safetyBreak5","awiabit":268,"len":1,"min":0.000000,"max":1.000000,"sign":false,"unit":"0/1","poly":[0.000000,1.000000]},
		{"key":"safetyBreak6","awiabit":269,"len":1,"min":0.000000,"max":1.000000,"sign":false,"unit":"0/1","poly":[0.000000,1.000000]},
		{"key":"safetyBreak7","awiabit":270,"len":1,"min":0.000000,"max":1.000000,"sign":false,"unit":"0/1","poly":[0.000000,1.000000]},
		{"key":"safetyBreak8","awiabit":271,"len":1,"min":0.000000,"max":1.000000,"sign":false,"unit":"0/1","poly":[0.000000,1.000000]},
		{"key":"safetyBreak9","awiabit":272,"len":1,"min":0.000000,"max":1.000000,"sign":false,"unit":"0/1","poly":[0.000000,1.000000]},
		{"key":"safetyBreak10","awiabit":273,"len":1,"min":0.000000,"max":1.000000,"sign":false,"unit":"0/1","poly":[0.000000,1.000000]},
		{"key":"safetyBreak11","awiabit":274,"len":1,"min":0.000000,"max":1.000000,"sign":false,"unit":"0/1","poly":[0.000000,1.000000]},
		{"key":"safetyBreak12","awiabit":275,"len":1,"min":0.000000,"max":1.000000,"sign":false,"unit":"0/1","poly":[0.000000,1.000000]},
		{"key":"safetyBreak13","awiabit":276,"len":1,"min":0.000000,"max":1.000000,"sign":false,"unit":"0/1","poly":[0.000000,1.000000]},
		{"key":"safetyBreak14","awiabit":277,"len":1,"min":0.000000,"max":1.000000,"sign":false,"unit":"0/1","poly":[0.000000,1.000000]},
		{"key":"safetyBreak15","awiabit":278,"len":1,"min":0.000000,"max":1.000000,"sign":false,"unit":"0/1","poly":[0.000000,1.000000]},
		{"key":"safetyBreak16","awiabit":279,"len":1,"min":0.000000,"max":1.000000,"sign":false,"unit":"0/1","poly":[0.000000,1.000000]},
		{"key":"ppoz1","awiabit":280,"len":1,"min":0.000000,"max":1.000000,"sign":false,"unit":"0/1","poly":[0.000000,1.000000]},
		{"key":"ppoz2","awiabit":281,"len":1,"min":0.000000,"max":1.000000,"sign":false,"unit":"0/1","poly":[0.000000,1.000000]},
		{"key":"ppoz3","awiabit":282,"len":1,"min":0.000000,"max":1.000000,"sign":false,"unit":"0/1","poly":[0.000000,1.000000]},
		{"key":"ppoz4","awiabit":283,"len":1,"min":0.000000,"max":1.000000,"sign":false,"unit":"0/1","poly":[0.000000,1.000000]},
		{"key":"ppoz5","awiabit":284,"len":1,"min":0.000000,"max":1.000000,"sign":false,"unit":"0/1","poly":[0.000000,1.000000]},
		{"key":"ppoz6","awiabit":285,"len":1,"min":0.000000,"max":1.000000,"sign":false,"unit":"0/1","poly":[0.000000,1.000000]},
		{"key":"ppoz7","awiabit":286,"len":1,"min":0.000000,"max":1.000000,"sign":false,"unit":"0/1","poly":[0.000000,1.000000]},
		{"key":"ppoz8","awiabit":287,"len":1,"min":0.000000,"max":1.000000,"sign":false,"unit":"0/1","poly":[0.000000,1.000000]},
		{"key":"ppoz9","awiabit":288,"len":1,"min":0.000000,"max":1.000000,"sign":false,"unit":"0/1","poly":[0.000000,1.000000]},
		{"key":"ppoz10","awiabit":289,"len":1,"min":0.000000,"max":1.000000,"sign":false,"unit":"0/1","poly":[0.000000,1.000000]},
		{"key":"ppoz11","awiabit":290,"len":1,"min":0.000000,"max":1.000000,"sign":false,"unit":"0/1","poly":[0.000000,1.000000]},
		{"key":"ppoz12","awiabit":291,"len":1,"min":0.000000,"max":1.000000,"sign":false,"unit":"0/1","poly":[0.000000,1.000000]},
		{"key":"ppoz13","awiabit":292,"len":1,"min":0.000000,"max":1.000000,"sign":false,"unit":"0/1","poly":[0.000000,1.000000]},
		{"key":"ppoz14","awiabit":293,"len":1,"min":0.000000,"max":1.000000,"sign":false,"unit":"0/1","poly":[0.000000,1.000000]},
		{"key":"ppoz15","awiabit":294,"len":1,"min":0.000000,"max":1.000000,"sign":false,"unit":"0/1","poly":[0.000000,1.000000]},
		{"key":"ppoz16","awiabit":295,"len":1,"min":0.000000,"max":1.000000,"sign":false,"unit":"0/1","poly":[0.000000,1.000000]},
		{"key":"ppoz17","awiabit":296,"len":1,"min":0.000000,"max":1.000000,"sign":false,"unit":"0/1","poly":[0.000000,1.000000]},
		{"key":"ppoz18","awiabit":297,"len":1,"min":0.000000,"max":1.000000,"sign":false,"unit":"0/1","poly":[0.000000,1.000000]},
		{"key":"ppoz19","awiabit":298,"len":1,"min":0.000000,"max":1.000000,"sign":false,"unit":"0/1","poly":[0.000000,1.000000]},
		{"key":"ppoz20","awiabit":299,"len":1,"min":0.000000,"max":1.000000,"sign":false,"unit":"0/1","poly":[0.000000,1.000000]},
		{"key":"ppoz21","awiabit":300,"len":1,"min":0.000000,"max":1.000000,"sign":false,"unit":"0/1","poly":[0.000000,1.000000]},
		{"key":"ppoz22","awiabit":301,"len":1,"min":0.000000,"max":1.000000,"sign":false,"unit":"0/1","poly":[0.000000,1.000000]},
		{"key":"ppoz23","awiabit":302,"len":1,"min":0.000000,"max":1.000000,"sign":false,"unit":"0/1","poly":[0.000000,1.000000]},
		{"key":"ppoz24","awiabit":303,"len":1,"min":0.000000,"max":1.000000,"sign":false,"unit":"0/1","poly":[0.000000,1.000000]},
		{"key":"ppoz25","awiabit":304,"len":1,"min":0.000000,"max":1.000000,"sign":false,"unit":"0/1","poly":[0.000000,1.000000]},
		{"key":"ppoz26","awiabit":305,"len":1,"min":0.000000,"max":1.000000,"sign":false,"unit":"0/1","poly":[0.000000,1.000000]},
		{"key":"ppoz27","awiabit":306,"len":1,"min":0.000000,"max":1.000000,"sign":false,"unit":"0/1","poly":[0.000000,1.000000]},
		{"key":"ppoz28","awiabit":307,"len":1,"min":0.000000,"max":1.000000,"sign":false,"unit":"0/1","poly":[0.000000,1.000000]},
		{"key":"ppoz29","awiabit":308,"len":1,"min":0.000000,"max":1.000000,"sign":false,"unit":"0/1","poly":[0.000000,1.000000]},
		{"key":"ppoz30","awiabit":309,"len":1,"min":0.000000,"max":1.000000,"sign":false,"unit":"0/1","poly":[0.000000,1.000000]},
		{"key":"ppoz31","awiabit":310,"len":1,"min":0.000000,"max":1.000000,"sign":false,"unit":"0/1","poly":[0.000000,1.000000]},
		{"key":"ppoz32","awiabit":311,"len":1,"min":0.000000,"max":1.000000,"sign":false,"unit":"0/1","poly":[0.000000,1.000000]},
		{"key":"ppoz33","awiabit":312,"len":1,"min":0.000000,"max":1.000000,"sign":false,"unit":"0/1","poly":[0.000000,1.000000]},
		{"key":"ppoz34","awiabit":313,"len":1,"min":0.000000,"max":1.000000,"sign":false,"unit":"0/1","poly":[0.000000,1.000000]},
		{"key":"ppoz35","awiabit":314,"len":1,"min":0.000000,"max":1.000000,"sign":false,"unit":"0/1","poly":[0.000000,1.000000]},
		{"key":"ppoz36","awiabit":315,"len":1,"min":0.000000,"max":1.000000,"sign":false,"unit":"0/1","poly":[0.000000,1.000000]},
		{"key":"ppoz37","awiabit":316,"len":1,"min":0.000000,"max":1.000000,"sign":false,"unit":"0/1","poly":[0.000000,1.000000]},
		{"key":"ppoz38","awiabit":317,"len":1,"min":0.000000,"max":1.000000,"sign":false,"unit":"0/1","poly":[0.000000,1.000000]},
		{"key":"ppoz39","awiabit":318,"len":1,"min":0.000000,"max":1.000000,"sign":false,"unit":"0/1","poly":[0.000000,1.000000]},
		{"key":"ppoz40","awiabit":319,"len":1,"min":0.000000,"max":1.000000,"sign":false,"unit":"0/1","poly":[0.000000,1.000000]},
		{"key":"vehicleNo","awiabit":320,"len":2,"min":0.000000,"max":3.000000,"sign":false,"unit":"-","poly":[0.000000,1.000000]},
		{"key":"isVehicleOn","awiabit":322,"len":1,"min":0.000000,"max":1.000000,"sign":false,"unit":"0/1","poly":[0.000000,1.000000]},
		{"key":"parking","awiabit":323,"len":1,"min":0.000000,"max":1.000000,"sign":false,"unit":"0/1","poly":[0.000000,1.000000]},
		{"key":"isForward","awiabit":324,"len":1,"min":0.000000,"max":1.000000,"sign":false,"unit":"0/1","poly":[0.000000,1.000000]},
		{"key":"isBackward","awiabit":325,"len":1,"min":0.000000,"max":1.000000,"sign":false,"unit":"0/1","poly":[0.000000,1.000000]},
		{"key":"rpjState","awiabit":326,"len":1,"min":0.000000,"max":1.000000,"sign":false,"unit":"0/1","poly":[0.000000,1.000000]},
		{"key":"battery","awiabit":327,"len":1,"min":0.000000,"max":1.000000,"sign":false,"unit":"0/1","poly":[0.000000,1.000000]},
		{"key":"reserveUserData","awiabit":328,"len":24,"min":0.000000,"max":16777215.000000,"sign":false,"unit":"-","poly":[0.000000,1.000000]},
		{"key":"overviewOdoP1","awiabit":352,"len":24,"min":0.000000,"max":16777215.000000,"sign":false,"unit":"km","poly":[0.000000,1.000000]},
		{"key":"overviewOdoP2","awiabit":376,"len":24,"min":0.000000,"max":16777215.000000,"sign":false,"unit":"km","poly":[0.000000,1.000000]},
		{"key":"overviewOdoP3","awiabit":400,"len":32,"min":0.000000,"max":4294967295.000000,"sign":false,"unit":"km","poly":[0.000000,1.000000]},
		{"key":"overviewDaysP1","awiabit":432,"len":16,"min":0.000000,"max":65535.000000,"sign":false,"unit":"km","poly":[0.000000,1.000000]},
		{"key":"overviewDaysP2","awiabit":448,"len":16,"min":0.000000,"max":65535.000000,"sign":false,"unit":"km","poly":[0.000000,1.000000]},
		{"key":"overviewDaysP3","awiabit":464,"len":24,"min":0.000000,"max":16777215.000000,"sign":false,"unit":"km","poly":[0.000000,1.000000]},
		{"key":"doorFault1","awiabit":488,"len":1,"min":0.000000,"max":1.000000,"sign":false,"unit":"0/1","poly":[0.000000,1.000000]},
		{"key":"doorFault2","awiabit":489,"len":1,"min":0.000000,"max":1.000000,"sign":false,"unit":"0/1","poly":[0.000000,1.000000]},
		{"key":"doorFault3","awiabit":490,"len":1,"min":0.000000,"max":1.000000,"sign":false,"unit":"0/1","poly":[0.000000,1.000000]},
		{"key":"doorFault4","awiabit":491,"len":1,"min":0.000000,"max":1.000000,"sign":false,"unit":"0/1","poly":[0.000000,1.000000]},
		{"key":"doorFault5","awiabit":492,"len":1,"min":0.000000,"max":1.000000,"sign":false,"unit":"0/1","poly":[0.000000,1.000000]},
		{"key":"doorFault6","awiabit":493,"len":1,"min":0.000000,"max":1.000000,"sign":false,"unit":"0/1","poly":[0.000000,1.000000]},
		{"key":"doorFault7","awiabit":494,"len":1,"min":0.000000,"max":1.000000,"sign":false,"unit":"0/1","poly":[0.000000,1.000000]},
		{"key":"doorFault8","awiabit":495,"len":1,"min":0.000000,"max":1.000000,"sign":false,"unit":"0/1","poly":[0.000000,1.000000]},
		{"key":"doorFault9","awiabit":496,"len":1,"min":0.000000,"max":1.000000,"sign":false,"unit":"0/1","poly":[0.000000,1.000000]},
		{"key":"doorFault10","awiabit":497,"len":1,"min":0.000000,"max":1.000000,"sign":false,"unit":"0/1","poly":[0.000000,1.000000]},
		{"key":"doorFault11","awiabit":498,"len":1,"min":0.000000,"max":1.000000,"sign":false,"unit":"0/1","poly":[0.000000,1.000000]},
		{"key":"doorFault12","awiabit":499,"len":1,"min":0.000000,"max":1.000000,"sign":false,"unit":"0/1","poly":[0.000000,1.000000]},
		{"key":"doorFault13","awiabit":500,"len":1,"min":0.000000,"max":1.000000,"sign":false,"unit":"0/1","poly":[0.000000,1.000000]},
		{"key":"doorFault14","awiabit":501,"len":1,"min":0.000000,"max":1.000000,"sign":false,"unit":"0/1","poly":[0.000000,1.000000]},
		{"key":"doorFault15","awiabit":502,"len":1,"min":0.000000,"max":1.000000,"sign":false,"unit":"0/1","poly":[0.000000,1.000000]},
		{"key":"doorFault16","awiabit":503,"len":1,"min":0.000000,"max":1.000000,"sign":false,"unit":"0/1","poly":[0.000000,1.000000]},
		{"key":"velocity","awiabit":504,"len":8,"min":0.000000,"max":190.000000,"sign":false,"unit":"km/h","poly":[0.000000,1.000000]},
		{"key":"doorButton1","awiabit":512,"len":1,"min":0.000000,"max":1.000000,"sign":false,"unit":"0/1","poly":[0.000000,1.000000]},
		{"key":"doorButton2","awiabit":513,"len":1,"min":0.000000,"max":1.000000,"sign":false,"unit":"0/1","poly":[0.000000,1.000000]},
		{"key":"doorButton3","awiabit":514,"len":1,"min":0.000000,"max":1.000000,"sign":false,"unit":"0/1","poly":[0.000000,1.000000]},
		{"key":"doorButton4","awiabit":515,"len":1,"min":0.000000,"max":1.000000,"sign":false,"unit":"0/1","poly":[0.000000,1.000000]},
		{"key":"doorButton5","awiabit":516,"len":1,"min":0.000000,"max":1.000000,"sign":false,"unit":"0/1","poly":[0.000000,1.000000]},
		{"key":"doorButton6","awiabit":517,"len":1,"min":0.000000,"max":1.000000,"sign":false,"unit":"0/1","poly":[0.000000,1.000000]},
		{"key":"doorButton7","awiabit":518,"len":1,"min":0.000000,"max":1.000000,"sign":false,"unit":"0/1","poly":[0.000000,1.000000]},
		{"key":"doorButton8","awiabit":519,"len":1,"min":0.000000,"max":1.000000,"sign":false,"unit":"0/1","poly":[0.000000,1.000000]},
		{"key":"doorButton9","awiabit":520,"len":1,"min":0.000000,"max":1.000000,"sign":false,"unit":"0/1","poly":[0.000000,1.000000]},
		{"key":"doorButton10","awiabit":521,"len":1,"min":0.000000,"max":1.000000,"sign":false,"unit":"0/1","poly":[0.000000,1.000000]},
		{"key":"doorButton11","awiabit":522,"len":1,"min":0.000000,"max":1.000000,"sign":false,"unit":"0/1","poly":[0.000000,1.000000]},
		{"key":"doorButton12","awiabit":523,"len":1,"min":0.000000,"max":1.000000,"sign":false,"unit":"0/1","poly":[0.000000,1.000000]},
		{"key":"doorButton13","awiabit":524,"len":1,"min":0.000000,"max":1.000000,"sign":false,"unit":"0/1","poly":[0.000000,1.000000]},
		{"key":"doorButton14","awiabit":525,"len":1,"min":0.000000,"max":1.000000,"sign":false,"unit":"0/1","poly":[0.000000,1.000000]},
		{"key":"doorButton15","awiabit":526,"len":1,"min":0.000000,"max":1.000000,"sign":false,"unit":"0/1","poly":[0.000000,1.000000]},
		{"key":"doorButton16","awiabit":527,"len":1,"min":0.000000,"max":1.000000,"sign":false,"unit":"0/1","poly":[0.000000,1.000000]},
	 	{"key":"doors1Off","awiabit":528,"len":1,"min":0.000000,"max":1.000000,"sign":false,"unit":"0/1","poly":[0.000000,1.000000]},
		{"key":"doors2Off","awiabit":529,"len":1,"min":0.000000,"max":1.000000,"sign":false,"unit":"0/1","poly":[0.000000,1.000000]},
		{"key":"doors3Off","awiabit":530,"len":1,"min":0.000000,"max":1.000000,"sign":false,"unit":"0/1","poly":[0.000000,1.000000]},
		{"key":"doors4Off","awiabit":531,"len":1,"min":0.000000,"max":1.000000,"sign":false,"unit":"0/1","poly":[0.000000,1.000000]},
		{"key":"doors5Off","awiabit":532,"len":1,"min":0.000000,"max":1.000000,"sign":false,"unit":"0/1","poly":[0.000000,1.000000]},
		{"key":"doors6Off","awiabit":533,"len":1,"min":0.000000,"max":1.000000,"sign":false,"unit":"0/1","poly":[0.000000,1.000000]},
		{"key":"doors7Off","awiabit":534,"len":1,"min":0.000000,"max":1.000000,"sign":false,"unit":"0/1","poly":[0.000000,1.000000]},
		{"key":"doors8Off","awiabit":535,"len":1,"min":0.000000,"max":1.000000,"sign":false,"unit":"0/1","poly":[0.000000,1.000000]},
		{"key":"doors9Off","awiabit":536,"len":1,"min":0.000000,"max":1.000000,"sign":false,"unit":"0/1","poly":[0.000000,1.000000]},
		{"key":"doors10Off","awiabit":537,"len":1,"min":0.000000,"max":1.000000,"sign":false,"unit":"0/1","poly":[0.000000,1.000000]},
		{"key":"doors11Off","awiabit":538,"len":1,"min":0.000000,"max":1.000000,"sign":false,"unit":"0/1","poly":[0.000000,1.000000]},
		{"key":"doors12Off","awiabit":539,"len":1,"min":0.000000,"max":1.000000,"sign":false,"unit":"0/1","poly":[0.000000,1.000000]},
		{"key":"doors13Off","awiabit":540,"len":1,"min":0.000000,"max":1.000000,"sign":false,"unit":"0/1","poly":[0.000000,1.000000]},
		{"key":"doors14Off","awiabit":541,"len":1,"min":0.000000,"max":1.000000,"sign":false,"unit":"0/1","poly":[0.000000,1.000000]},
		{"key":"doors15Off","awiabit":542,"len":1,"min":0.000000,"max":1.000000,"sign":false,"unit":"0/1","poly":[0.000000,1.000000]},
		{"key":"doors16Off","awiabit":543,"len":1,"min":0.000000,"max":1.000000,"sign":false,"unit":"0/1","poly":[0.000000,1.000000]},
		{"key":"doors1Opened","awiabit":544,"len":1,"min":0.000000,"max":1.000000,"sign":false,"unit":"0/1","poly":[0.000000,1.000000]},
	 	{"key":"doors2Opened","awiabit":545,"len":1,"min":0.000000,"max":1.000000,"sign":false,"unit":"0/1","poly":[0.000000,1.000000]},
		{"key":"doors3Opened","awiabit":546,"len":1,"min":0.000000,"max":1.000000,"sign":false,"unit":"0/1","poly":[0.000000,1.000000]},
		{"key":"doors4Opened","awiabit":547,"len":1,"min":0.000000,"max":1.000000,"sign":false,"unit":"0/1","poly":[0.000000,1.000000]},
		{"key":"doors5Opened","awiabit":548,"len":1,"min":0.000000,"max":1.000000,"sign":false,"unit":"0/1","poly":[0.000000,1.000000]},
		{"key":"doors6Opened","awiabit":549,"len":1,"min":0.000000,"max":1.000000,"sign":false,"unit":"0/1","poly":[0.000000,1.000000]},
		{"key":"doors7Opened","awiabit":550,"len":1,"min":0.000000,"max":1.000000,"sign":false,"unit":"0/1","poly":[0.000000,1.000000]},
		{"key":"doors8Opened","awiabit":551,"len":1,"min":0.000000,"max":1.000000,"sign":false,"unit":"0/1","poly":[0.000000,1.000000]},
		{"key":"doors9Opened","awiabit":552,"len":1,"min":0.000000,"max":1.000000,"sign":false,"unit":"0/1","poly":[0.000000,1.000000]},
		{"key":"doors10Opened","awiabit":553,"len":1,"min":0.000000,"max":1.000000,"sign":false,"unit":"0/1","poly":[0.000000,1.000000]},
		{"key":"doors11Opened","awiabit":554,"len":1,"min":0.000000,"max":1.000000,"sign":false,"unit":"0/1","poly":[0.000000,1.000000]},
		{"key":"doors12Opened","awiabit":555,"len":1,"min":0.000000,"max":1.000000,"sign":false,"unit":"0/1","poly":[0.000000,1.000000]},
		{"key":"doors13Opened","awiabit":556,"len":1,"min":0.000000,"max":1.000000,"sign":false,"unit":"0/1","poly":[0.000000,1.000000]},
		{"key":"doors14Opened","awiabit":557,"len":1,"min":0.000000,"max":1.000000,"sign":false,"unit":"0/1","poly":[0.000000,1.000000]},
		{"key":"doors15Opened","awiabit":558,"len":1,"min":0.000000,"max":1.000000,"sign":false,"unit":"0/1","poly":[0.000000,1.000000]},
		{"key":"doors16Opened","awiabit":559,"len":1,"min":0.000000,"max":1.000000,"sign":false,"unit":"0/1","poly":[0.000000,1.000000]},
		{"key":"sos1Cripple","awiabit":560,"len":1,"min":0.000000,"max":1.000000,"sign":false,"unit":"0/1","poly":[0.000000,1.000000]},
		{"key":"sos2Cripple","awiabit":561,"len":1,"min":0.000000,"max":1.000000,"sign":false,"unit":"0/1","poly":[0.000000,1.000000]},
		{"key":"sos1Wc","awiabit":562,"len":1,"min":0.000000,"max":1.000000,"sign":false,"unit":"0/1","poly":[0.000000,1.000000]},
		{"key":"sos2Wc","awiabit":563,"len":1,"min":0.000000,"max":1.000000,"sign":false,"unit":"0/1","poly":[0.000000,1.000000]},
		{"key":"wsOn","awiabit":564,"len":1,"min":0.000000,"max":1.000000,"sign":false,"unit":"0/1","poly":[0.000000,1.000000]},
		{"key":"fullLight","awiabit":565,"len":1,"min":0.000000,"max":1.000000,"sign":false,"unit":"0/1","poly":[0.000000,1.000000]},
		{"key":"halfLight","awiabit":566,"len":1,"min":0.000000,"max":1.000000,"sign":false,"unit":"0/1","poly":[0.000000,1.000000]},
		{"key":"emergencyLight","awiabit":567,"len":1,"min":0.000000,"max":1.000000,"sign":false,"unit":"0/1","poly":[0.000000,1.000000]},
		{"key":"reserve3","awiabit":568,"len":8,"min":0.000000,"max":255.000000,"sign":false,"unit":"-","poly":[0.000000,1.000000]}
      ],
      "lenbit":576
    }
  ]
}

